cathpy/core/__init__.py
cathpy/core/align.py
cathpy/core/datafiles.py
cathpy/core/error.py
cathpy/core/funfhmmer.py
cathpy/core/models.py
cathpy/core/release.py
cathpy/core/ssap.py
cathpy/core/tasks.py
cathpy/core/tests.py
cathpy/core/util.py
cathpy/core/version.py
cathpy/core/scripts/__init__.py
cathpy/core/scripts/cath_cli.py
cathpy/core/tools/GroupSim/README.md
cathpy/core/tools/GroupSim/group_sim_sdp.py
cathpy/core/tools/GroupSim/group_sim_sdp_without_cons.py
cathpy/core/tools/GroupSim/groupsim2jalview.pl
cathpy/core/tools/GroupSim/mclachlan1972.aa.dat
cathpy/core/tools/GroupSim/mclachlan1972.dat
cathpy/core/tools/darwin-x86_64/cath-cluster
cathpy/core/tools/darwin-x86_64/cath-resolve-hits
cathpy/core/tools/darwin-x86_64/cath-ssap
cathpy/core/tools/darwin-x86_64/cath-superpose
cathpy/core/tools/darwin-x86_64/scorecons
cathpy/core/tools/data/PET91mod.mat2
cathpy/core/tools/linux-x86_64/cath-cluster
cathpy/core/tools/linux-x86_64/cath-resolve-hits
cathpy/core/tools/linux-x86_64/cath-ssap
cathpy/core/tools/linux-x86_64/cath-superpose
cathpy/core/tools/linux-x86_64/scorecons
cathpy-0.4.1.data/scripts/cath-align-scorecons
cathpy-0.4.1.data/scripts/cath-align-summary
cathpy-0.4.1.data/scripts/cath-funfhmmer-api
cathpy-0.4.1.data/scripts/cath-sc-merge-alignment
cathpy-0.4.1.dist-info/LICENSE
cathpy-0.4.1.dist-info/METADATA
cathpy-0.4.1.dist-info/WHEEL
cathpy-0.4.1.dist-info/entry_points.txt
cathpy-0.4.1.dist-info/top_level.txt
cathpy-0.4.1.dist-info/RECORD
