Metadata-Version: 2.1
Name: cathpy
Version: 0.4.1
Summary: CathPy - Python Bioinformatics Toolkit for CATH (Protein Classification).
Home-page: https://github.com/UCL/cathpy
Author: Ian Sillitoe
Author-email: i.sillitoe@ucl.ac.uk
License: UNKNOWN
Platform: UNKNOWN
Classifier: Programming Language :: Python :: 3
Classifier: License :: OSI Approved :: MIT License
Classifier: Operating System :: OS Independent
License-File: LICENSE
Requires-Dist: Click
Requires-Dist: requests
Requires-Dist: jsonpickle
Requires-Dist: tqdm
Requires-Dist: dendropy
Requires-Dist: redis
Requires-Dist: celery
Requires-Dist: pymongo
